landon/async/__init__.py
landon/async/landon.py
landon/sync/__init__.py
landon/sync/landon.py
landon-1.1.0.dist-info/LICENSE
landon-1.1.0.dist-info/METADATA
landon-1.1.0.dist-info/WHEEL
landon-1.1.0.dist-info/top_level.txt
landon-1.1.0.dist-info/RECORD
